<?xml version="1.0" encoding="utf-8" standalone="no" ?>
<wheel>
    <default>
        <physics radius="0.972" width="0.65" mass="0.295" tireType="mud" frictionScale="1.60" maxLongStiffness="8" maxLatStiffness="100" maxLatStiffnessLoad="2" />
        <tire filename="$data/shared/wheels/mitas/SFT/R38_SFT.i3d" nodeLeft="1|0" nodeRight="1|0" maxDeformation="0.098" isCareWheel="false" tireTrackAtlasIndex="0" />
        <outerRim filename="$data/shared/wheels/rims/rim001.i3d" node="1|0" widthAndDiam="21 38" />
        <innerRim filename="$data/shared/wheels/rims/rim001.i3d" nodeLeft="3|0" nodeRight="3|1" widthAndDiam="21 38" />
    </default>
		<configurations>
        <configuration id="dual" >
            <innerRim filename="-" nodeLeft="-" nodeRight="-" widthAndDiam="-" />
        </configuration>
          </configurations>
</wheel>
